pyre_gevent/__init__.py
pyre_gevent/pyre.py
pyre_gevent/pyre_event.py
pyre_gevent/pyre_group.py
pyre_gevent/pyre_node.py
pyre_gevent/pyre_peer.py
pyre_gevent/zactor.py
pyre_gevent/zbeacon.py
pyre_gevent/zhelper.py
pyre_gevent/zre_msg.py
pyre_gevent/zsocket.py
pyre_gevent-0.3.5.dist-info/licenses/AUTHORS
pyre_gevent-0.3.5.dist-info/licenses/LICENSE
pyre_gevent-0.3.5.dist-info/METADATA
pyre_gevent-0.3.5.dist-info/WHEEL
pyre_gevent-0.3.5.dist-info/top_level.txt
pyre_gevent-0.3.5.dist-info/RECORD
