Metadata-Version: 2.4
Name: pyre-gevent
Version: 0.3.5
Summary: Python ZRE implementation (green version)
Home-page: http://www.github.com/tangb/pyre-gevent/
Author: Arnaud Loonstra
Author-email: arnaud@sphaero.org
Maintainer: Tanguy Bonneau
Maintainer-email: tanguy.bonneau@gmail.com
License-File: LICENSE
License-File: AUTHORS
Requires-Dist: pyzmq
Requires-Dist: ipaddress
Requires-Dist: netaddr
Requires-Dist: netifaces-plus
Dynamic: author
Dynamic: author-email
Dynamic: home-page
Dynamic: license-file
Dynamic: maintainer
Dynamic: maintainer-email
Dynamic: requires-dist
Dynamic: summary
